init_checks/__init__.py
init_checks/check_env_vars.py
init_checks/install_hook.py
init_checks-0.1.9.dist-info/METADATA
init_checks-0.1.9.dist-info/WHEEL
init_checks-0.1.9.dist-info/entry_points.txt
init_checks-0.1.9.dist-info/top_level.txt
init_checks-0.1.9.dist-info/RECORD
