Metadata-Version: 2.1
Name: init_checks
Version: 0.1.9
Classifier: Programming Language :: Python :: 3
Classifier: License :: OSI Approved :: MIT License
Classifier: Operating System :: OS Independent
Requires-Python: >=3.6
Requires-Dist: pyyaml
Requires-Dist: pre-commit
Requires-Dist: tabulate
